[
  {
    "name": "Customer Portal",
    "tier": "tier_1",
    "internet_facing": true,
    "business_function": "Consumer web banking and account management",
    "owner": {"team": "Digital Channels", "lead": "Maya Patel", "email": "maya.patel@harborview.example"},
    "maintenance_window": {"day_of_week": "thursday", "start_hour_24": 22, "duration_hours": 2},
    "rollback_complexity": "medium",
    "components": ["express", "react", "axios", "jsonwebtoken", "lodash", "material-ui"],
    "customer_facing": true,
    "regulatory_scope": ["PCI-DSS", "SOX"],
    "hosting_type": "aws",
    "environment": "prod"
  },
  {
    "name": "Mobile Banking App",
    "tier": "tier_1",
    "internet_facing": true,
    "business_function": "Consumer mobile banking with biometric auth",
    "owner": {"team": "Digital Channels", "lead": "Maya Patel", "email": "maya.patel@harborview.example"},
    "maintenance_window": {"day_of_week": "tuesday", "start_hour_24": 21, "duration_hours": 2},
    "rollback_complexity": "medium",
    "components": ["alamofire", "keychainaccess", "cryptokit", "retrofit", "okhttp", "room"],
    "customer_facing": true,
    "regulatory_scope": ["PCI-DSS"],
    "hosting_type": "hybrid",
    "environment": "prod"
  },
  {
    "name": "Auth Service",
    "tier": "tier_1",
    "internet_facing": false,
    "business_function": "Authentication, authorization, and session management",
    "owner": {"team": "Identity Platform", "lead": "Jordan Lee", "email": "jordan.lee@harborview.example"},
    "maintenance_window": {"day_of_week": "wednesday", "start_hour_24": 23, "duration_hours": 2},
    "rollback_complexity": "high",
    "components": ["nestjs", "passport", "bcrypt", "jsonwebtoken", "rate-limiter-flexible"],
    "customer_facing": false,
    "regulatory_scope": ["SOC2", "PCI-DSS"],
    "hosting_type": "aws",
    "environment": "prod"
  },
  {
    "name": "Payment Gateway",
    "tier": "tier_1",
    "internet_facing": true,
    "business_function": "Card and ACH transaction routing and settlement",
    "owner": {"team": "Payments Engineering", "lead": "Arjun Shah", "email": "arjun.shah@harborview.example"},
    "maintenance_window": {"day_of_week": "saturday", "start_hour_24": 2, "duration_hours": 3},
    "rollback_complexity": "high",
    "components": ["spring-boot", "jpos", "kafka", "hibernate", "bouncy-castle", "resilience4j"],
    "customer_facing": true,
    "regulatory_scope": ["PCI-DSS", "SOX", "FFIEC"],
    "hosting_type": "aws",
    "environment": "prod"
  },
  {
    "name": "Core Banking System",
    "tier": "tier_1",
    "internet_facing": false,
    "business_function": "Ledger, account posting, and balance management",
    "owner": {"team": "Core Banking", "lead": "Evelyn Brooks", "email": "evelyn.brooks@harborview.example"},
    "maintenance_window": {"day_of_week": "sunday", "start_hour_24": 2, "duration_hours": 4},
    "rollback_complexity": "high",
    "components": ["db2-jdbc", "mq-client", "cobol-runtime", "jzos"],
    "customer_facing": false,
    "regulatory_scope": ["SOX", "FFIEC", "GLBA"],
    "hosting_type": "on_prem",
    "environment": "prod"
  },
  {
    "name": "CRM",
    "tier": "tier_3",
    "internet_facing": false,
    "business_function": "Customer support, relationship management, and campaigns",
    "owner": {"team": "Customer Ops Tech", "lead": "Rina Gomez", "email": "rina.gomez@harborview.example"},
    "maintenance_window": {"day_of_week": "friday", "start_hour_24": 20, "duration_hours": 2},
    "rollback_complexity": "low",
    "components": ["salesforce-sdk", "lodash", "axios"],
    "customer_facing": false,
    "regulatory_scope": [],
    "hosting_type": "saas",
    "environment": "prod"
  },
  {
    "name": "Reporting & Analytics Engine",
    "tier": "tier_2",
    "internet_facing": false,
    "business_function": "Business intelligence, dashboards, and regulatory reporting",
    "owner": {"team": "Data Engineering", "lead": "Priya Narang", "email": "priya.narang@harborview.example"},
    "maintenance_window": {"day_of_week": "sunday", "start_hour_24": 4, "duration_hours": 2},
    "rollback_complexity": "medium",
    "components": ["pandas", "numpy", "sqlalchemy", "matplotlib", "airflow"],
    "customer_facing": false,
    "regulatory_scope": ["SOX"],
    "hosting_type": "aws",
    "environment": "prod"
  },
  {
    "name": "Data Warehouse",
    "tier": "tier_2",
    "internet_facing": false,
    "business_function": "Central analytical data store and ETL pipeline",
    "owner": {"team": "Data Platform", "lead": "Priya Narang", "email": "priya.narang@harborview.example"},
    "maintenance_window": {"day_of_week": "sunday", "start_hour_24": 5, "duration_hours": 2},
    "rollback_complexity": "medium",
    "components": ["redshift-driver", "aws-glue", "psycopg2", "boto3"],
    "customer_facing": false,
    "regulatory_scope": ["SOX"],
    "hosting_type": "aws",
    "environment": "prod"
  },
  {
    "name": "Fraud Detection Service",
    "tier": "tier_1",
    "internet_facing": false,
    "business_function": "Real-time transaction risk scoring and fraud prevention",
    "owner": {"team": "Risk Engineering", "lead": "Samir Kulkarni", "email": "samir.kulkarni@harborview.example"},
    "maintenance_window": {"day_of_week": "saturday", "start_hour_24": 3, "duration_hours": 2},
    "rollback_complexity": "medium",
    "components": ["scikit-learn", "tensorflow", "xgboost", "pandas", "joblib"],
    "customer_facing": false,
    "regulatory_scope": ["BSA/AML", "FFIEC"],
    "hosting_type": "aws",
    "environment": "prod"
  },
  {
    "name": "Regulatory Compliance Service",
    "tier": "tier_2",
    "internet_facing": false,
    "business_function": "Policy enforcement, audit workflows, and compliance checks",
    "owner": {"team": "Compliance Technology", "lead": "Nadia Ross", "email": "nadia.ross@harborview.example"},
    "maintenance_window": {"day_of_week": "friday", "start_hour_24": 23, "duration_hours": 2},
    "rollback_complexity": "medium",
    "components": ["opa-client", "ajv", "oas-tools", "jsonschema"],
    "customer_facing": false,
    "regulatory_scope": ["SOX", "GLBA", "BSA/AML"],
    "hosting_type": "aws",
    "environment": "prod"
  },
  {
    "name": "Notification Service",
    "tier": "tier_3",
    "internet_facing": false,
    "business_function": "Email, SMS, and push notification delivery",
    "owner": {"team": "Platform Messaging", "lead": "Lena White", "email": "lena.white@harborview.example"},
    "maintenance_window": {"day_of_week": "monday", "start_hour_24": 22, "duration_hours": 2},
    "rollback_complexity": "low",
    "components": ["twilio-sdk", "sendgrid-sdk", "nodemailer", "bullmq"],
    "customer_facing": false,
    "regulatory_scope": [],
    "hosting_type": "aws",
    "environment": "prod"
  },
  {
    "name": "Identity & Access Management (IAM)",
    "tier": "tier_1",
    "internet_facing": false,
    "business_function": "Enterprise identity provider and service-to-service authentication",
    "owner": {"team": "Identity Platform", "lead": "Jordan Lee", "email": "jordan.lee@harborview.example"},
    "maintenance_window": {"day_of_week": "wednesday", "start_hour_24": 22, "duration_hours": 2},
    "rollback_complexity": "high",
    "components": ["keycloak", "spring-security", "bouncy-castle"],
    "customer_facing": false,
    "regulatory_scope": ["SOC2", "PCI-DSS", "FFIEC"],
    "hosting_type": "on_prem",
    "environment": "prod"
  }
]
